just_a_test_002/__init__.py
just_a_test_002/test.py
just_a_test_002-5.0.0.dist-info/DESCRIPTION.rst
just_a_test_002-5.0.0.dist-info/METADATA
just_a_test_002-5.0.0.dist-info/RECORD
just_a_test_002-5.0.0.dist-info/WHEEL
just_a_test_002-5.0.0.dist-info/metadata.json
just_a_test_002-5.0.0.dist-info/top_level.txt
